// class version 52.0 (52)
// access flags 0x21
public class edu/cmu/cs/mvelezce/implicit/Test implements edu/columbia/cs/psl/phosphor/struct/TaintedWithObjTag  {


  @Ledu/columbia/cs/psl/phosphor/runtime/TaintInstrumented;() // invisible
  // compiled from: Test.java

  // access flags 0x1
  public <init>(Ledu/columbia/cs/psl/phosphor/struct/ControlTaintTagStack;Ledu/columbia/cs/psl/phosphor/runtime/TaintSentinel;)V
   L0
   L1
   L2
    LINENUMBER 6 L2
    ALOAD 0
    INVOKESPECIAL java/lang/Object.<init> ()V
    RETURN
   L3
    LOCALVARIABLE this Ledu/cmu/cs/mvelezce/implicit/Test; L2 L3 0
   L4
    LOCALVARIABLE phosphorJumpControlTag Ledu/columbia/cs/psl/phosphor/struct/ControlTaintTagStack; L0 L4 1
   L5
   L6
   FRAME FULL [T edu/columbia/cs/psl/phosphor/struct/ControlTaintTagStack] [java/lang/Throwable]
    ATHROW
    MAXSTACK = 101
    MAXLOCALS = 3

  // access flags 0x9
  public static main$$PHOSPHORTAGGED([Ljava/lang/String;Ledu/columbia/cs/psl/phosphor/struct/ControlTaintTagStack;)V
    TRYCATCHBLOCK L0 L1 L2 null
   L0
   L3
   L4
   L5
    LINENUMBER 9 L5
    ALOAD 1
    INVOKESTATIC edu/cmu/cs/mvelezce/implicit/Test.testExample2$$PHOSPHORTAGGED (Ledu/columbia/cs/psl/phosphor/struct/ControlTaintTagStack;)V
   L6
    LINENUMBER 10 L6
    RETURN
   L7
    LOCALVARIABLE args [Ljava/lang/String; L5 L7 0
   L8
    LOCALVARIABLE phosphorJumpControlTag Ledu/columbia/cs/psl/phosphor/struct/ControlTaintTagStack; L3 L8 1
    LOCALVARIABLE PhopshorImplicitTaintTrackingFromParent Ledu/columbia/cs/psl/phosphor/struct/ControlTaintTagStack; L5 L7 1
   L1
   L2
   FRAME FULL [T edu/columbia/cs/psl/phosphor/struct/ControlTaintTagStack] [java/lang/Throwable]
    ATHROW
    MAXSTACK = 100
    MAXLOCALS = 2

  // access flags 0x9
  public static testExample2$$PHOSPHORTAGGED(Ledu/columbia/cs/psl/phosphor/struct/ControlTaintTagStack;)V
   L0
    ACONST_NULL
    ASTORE 1
    ACONST_NULL
    ASTORE 2
    ACONST_NULL
    ASTORE 3
    ACONST_NULL
    ASTORE 4
    TRYCATCHBLOCK L1 L2 L3 null
   L1
   L4
   L5
    NEW edu/columbia/cs/psl/phosphor/struct/TaintedIntWithObjTag
    DUP
    INVOKESPECIAL edu/columbia/cs/psl/phosphor/struct/TaintedIntWithObjTag.<init> ()V
    DUP
    ALOAD 0
    INVOKESTATIC edu/columbia/cs/psl/phosphor/runtime/Taint.combineTagsOnObject (Ljava/lang/Object;Ledu/columbia/cs/psl/phosphor/struct/ControlTaintTagStack;)V
    ASTORE 5
   L6
    NEW edu/columbia/cs/psl/phosphor/struct/TaintedBooleanWithObjTag
    DUP
    INVOKESPECIAL edu/columbia/cs/psl/phosphor/struct/TaintedBooleanWithObjTag.<init> ()V
    DUP
    ALOAD 0
    INVOKESTATIC edu/columbia/cs/psl/phosphor/runtime/Taint.combineTagsOnObject (Ljava/lang/Object;Ledu/columbia/cs/psl/phosphor/struct/ControlTaintTagStack;)V
    ASTORE 6
   L7
   L8
    LINENUMBER 13 L8
    ALOAD 0
    INVOKEVIRTUAL edu/columbia/cs/psl/phosphor/struct/ControlTaintTagStack.copyTag ()Ledu/columbia/cs/psl/phosphor/runtime/Taint;
    ICONST_1
    ALOAD 0
    ALOAD 6
    INVOKESTATIC edu/cmu/cs/mvelezce/taints/Sources.A_0$$PHOSPHORTAGGED (Ledu/columbia/cs/psl/phosphor/runtime/Taint;ZLedu/columbia/cs/psl/phosphor/struct/ControlTaintTagStack;Ledu/columbia/cs/psl/phosphor/struct/TaintedBooleanWithObjTag;)Ledu/columbia/cs/psl/phosphor/struct/TaintedBooleanWithObjTag;
    DUP
    GETFIELD edu/columbia/cs/psl/phosphor/struct/TaintedBooleanWithObjTag.taint : Ledu/columbia/cs/psl/phosphor/runtime/Taint;
    SWAP
    GETFIELD edu/columbia/cs/psl/phosphor/struct/TaintedBooleanWithObjTag.val : Z
    SWAP
    ALOAD 0
    INVOKESTATIC edu/columbia/cs/psl/phosphor/runtime/Taint.combineTags (Ledu/columbia/cs/psl/phosphor/runtime/Taint;Ledu/columbia/cs/psl/phosphor/struct/ControlTaintTagStack;)Ledu/columbia/cs/psl/phosphor/runtime/Taint;
    SWAP
   L9
    ISTORE 7
    INVOKESTATIC edu/columbia/cs/psl/phosphor/runtime/Taint.copyTaint (Ledu/columbia/cs/psl/phosphor/runtime/Taint;)Ledu/columbia/cs/psl/phosphor/runtime/Taint;
    ASTORE 8
   L10
    LINENUMBER 14 L10
    ALOAD 0
    INVOKEVIRTUAL edu/columbia/cs/psl/phosphor/struct/ControlTaintTagStack.copyTag ()Ledu/columbia/cs/psl/phosphor/runtime/Taint;
    ICONST_1
    ALOAD 0
    ALOAD 6
    INVOKESTATIC edu/cmu/cs/mvelezce/taints/Sources.B_1$$PHOSPHORTAGGED (Ledu/columbia/cs/psl/phosphor/runtime/Taint;ZLedu/columbia/cs/psl/phosphor/struct/ControlTaintTagStack;Ledu/columbia/cs/psl/phosphor/struct/TaintedBooleanWithObjTag;)Ledu/columbia/cs/psl/phosphor/struct/TaintedBooleanWithObjTag;
    DUP
    GETFIELD edu/columbia/cs/psl/phosphor/struct/TaintedBooleanWithObjTag.taint : Ledu/columbia/cs/psl/phosphor/runtime/Taint;
    SWAP
    GETFIELD edu/columbia/cs/psl/phosphor/struct/TaintedBooleanWithObjTag.val : Z
    SWAP
    ALOAD 0
    INVOKESTATIC edu/columbia/cs/psl/phosphor/runtime/Taint.combineTags (Ledu/columbia/cs/psl/phosphor/runtime/Taint;Ledu/columbia/cs/psl/phosphor/struct/ControlTaintTagStack;)Ledu/columbia/cs/psl/phosphor/runtime/Taint;
    SWAP
   L11
    ISTORE 9
    INVOKESTATIC edu/columbia/cs/psl/phosphor/runtime/Taint.copyTaint (Ledu/columbia/cs/psl/phosphor/runtime/Taint;)Ledu/columbia/cs/psl/phosphor/runtime/Taint;
    ASTORE 15
   L12
    LINENUMBER 16 L12
    ALOAD 0
    INVOKEVIRTUAL edu/columbia/cs/psl/phosphor/struct/ControlTaintTagStack.copyTag ()Ledu/columbia/cs/psl/phosphor/runtime/Taint;
    ICONST_0
    SWAP
    ALOAD 0
    INVOKESTATIC edu/columbia/cs/psl/phosphor/runtime/Taint.combineTags (Ledu/columbia/cs/psl/phosphor/runtime/Taint;Ledu/columbia/cs/psl/phosphor/struct/ControlTaintTagStack;)Ledu/columbia/cs/psl/phosphor/runtime/Taint;
    SWAP
   L13
    ISTORE 10
    INVOKESTATIC edu/columbia/cs/psl/phosphor/runtime/Taint.copyTaint (Ledu/columbia/cs/psl/phosphor/runtime/Taint;)Ledu/columbia/cs/psl/phosphor/runtime/Taint;
    ASTORE 16
   L14
    LINENUMBER 17 L14
    LDC "Miguel"
    DUP
    ALOAD 0
    INVOKESTATIC edu/columbia/cs/psl/phosphor/runtime/Taint.combineTagsOnObject (Ljava/lang/Object;Ledu/columbia/cs/psl/phosphor/struct/ControlTaintTagStack;)V
    ASTORE 11
   L15
    LINENUMBER 18 L15
    ALOAD 0
    INVOKEVIRTUAL edu/columbia/cs/psl/phosphor/struct/ControlTaintTagStack.copyTag ()Ledu/columbia/cs/psl/phosphor/runtime/Taint;
    LCONST_0
    DUP2_X1
    POP2
    ALOAD 0
    INVOKESTATIC edu/columbia/cs/psl/phosphor/runtime/Taint.combineTags (Ledu/columbia/cs/psl/phosphor/runtime/Taint;Ledu/columbia/cs/psl/phosphor/struct/ControlTaintTagStack;)Ledu/columbia/cs/psl/phosphor/runtime/Taint;
    DUP_X2
    POP
   L16
    LSTORE 12
    INVOKESTATIC edu/columbia/cs/psl/phosphor/runtime/Taint.copyTaint (Ledu/columbia/cs/psl/phosphor/runtime/Taint;)Ledu/columbia/cs/psl/phosphor/runtime/Taint;
    ASTORE 17
   L17
    LINENUMBER 19 L17
    ALOAD 0
    INVOKEVIRTUAL edu/columbia/cs/psl/phosphor/struct/ControlTaintTagStack.copyTag ()Ledu/columbia/cs/psl/phosphor/runtime/Taint;
    ICONST_0
    SWAP
    ALOAD 0
    INVOKESTATIC edu/columbia/cs/psl/phosphor/runtime/Taint.combineTags (Ledu/columbia/cs/psl/phosphor/runtime/Taint;Ledu/columbia/cs/psl/phosphor/struct/ControlTaintTagStack;)Ledu/columbia/cs/psl/phosphor/runtime/Taint;
    SWAP
   L18
    ISTORE 14
    INVOKESTATIC edu/columbia/cs/psl/phosphor/runtime/Taint.copyTaint (Ledu/columbia/cs/psl/phosphor/runtime/Taint;)Ledu/columbia/cs/psl/phosphor/runtime/Taint;
    ASTORE 18
   L19
    LINENUMBER 21 L19
   L20
    ALOAD 8
    ILOAD 7
    SWAP
    ALOAD 0
    SWAP
    ALOAD 1
    INVOKEVIRTUAL edu/columbia/cs/psl/phosphor/struct/ControlTaintTagStack.push (Ledu/columbia/cs/psl/phosphor/runtime/Taint;Ledu/columbia/cs/psl/phosphor/struct/EnqueuedTaint;)Ledu/columbia/cs/psl/phosphor/struct/EnqueuedTaint;
    ASTORE 1
    INVOKESTATIC edu/cmu/cs/mvelezce/taints/Sinks.sink (Ljava/lang/Object;)V
    IFEQ L21
